gazi/__init__.py
gazi/app.py
gazi/request.py
gazi/response.py
gazi/route.py
gazi-0.1.5.dist-info/LICENSE
gazi-0.1.5.dist-info/METADATA
gazi-0.1.5.dist-info/WHEEL
gazi-0.1.5.dist-info/top_level.txt
gazi-0.1.5.dist-info/RECORD
