Metadata-Version: 2.1
Name: gazi
Version: 0.1.5
Summary: A lightweight, class-based, easy-to-use ASGI framework
Home-page: https://github.com/akiacode/gazi
Author: Catry
License: MIT
Project-URL: Bug Tracker, https://github.com/akiacode/gazi/issues
Platform: UNKNOWN
Classifier: Programming Language :: Python :: 3
Classifier: License :: OSI Approved :: MIT License
Classifier: Operating System :: OS Independent
Requires-Python: >=3.6
License-File: LICENSE
